wubi/__init__.py
wubi/_compat.py
wubi/build_map.py
wubi/cmd.py
wubi/cw.py
wubi/wc.py
wubi/wubi.pickle
wubi/wubi.py
wubi-1.0.dist-info/DESCRIPTION.rst
wubi-1.0.dist-info/METADATA
wubi-1.0.dist-info/RECORD
wubi-1.0.dist-info/WHEEL
wubi-1.0.dist-info/entry_points.txt
wubi-1.0.dist-info/metadata.json
wubi-1.0.dist-info/top_level.txt
